{
    "ausfertigung": 2,
    "loecher": {
        "gremien": false,
        "sp": false
    },
    "nummer": 1040214,
    "semester": "Wintersemester 2016/2017",
    "stud": {
        "ausweistyp": "zweithoerer",
        "beurlaubt": false,
        "fakultaet": 6,
        "geburtsdatum": "11.07.1999",
        "matrikelnummer": 2576276,
        "mehrfachausfertigung": 2,
        "mitglied_studierendenschaft": true,
        "nachname": "L\u00fcbben",
        "plzort": "53222 Bonn",
        "sternchen": 0,
        "strasse": "Sylvanerweg 18a",
        "studienfaecher": [
            {
                "abschluss": "Promotion",
                "fach": "Physik",
                "fsem": 7
            }
        ],
        "vorname": "Hiltraut",
        "weiblich": true
    }
}
