{
    "ausfertigung": 1,
    "loecher": {
        "gremien": true,
        "sp": true
    },
    "nummer": 2169253,
    "semester": "Wintersemester 2016/2017",
    "stud": {
        "beurlaubt": false,
        "fakultaet": 6,
        "geburtsdatum": "07.08.1996",
        "matrikelnummer": 2748413,
        "mehrfachausfertigung": 1,
        "nachname": "Fritzsch",
        "plzort": "67316 Carlsberg",
        "sternchen": 0,
        "strasse": "Elisabethenplatz 9",
        "studienfaecher": [
            {
                "abschluss": "Master of Disaster",
                "fach": "Katastrophenmanagement",
                "fsem": 0
            }
        ],
        "vorname": "Hansl",
        "weiblich": false
    }
}
