{
    "ausfertigung": 2,
    "loecher": {
        "gremien": false,
        "sp": false
    },
    "nummer": 2994999,
    "semester": "Wintersemester 2016/2017",
    "stud": {
        "beurlaubt": false,
        "fakultaet": 6,
        "geburtsdatum": "25.04.1994",
        "matrikelnummer": 2830437,
        "mehrfachausfertigung": 2,
        "nachname": "Hamacher",
        "plzort": "53199 Bonn",
        "sternchen": 0,
        "strasse": "K\u00f6nigsufer 2",
        "studienfaecher": [
            {
                "abschluss": "Master of Disaster",
                "fach": "Katastrophenmanagement",
                "fsem": 0
            }
        ],
        "vorname": "Haymo",
        "weiblich": false
    }
}
