{
    "ausfertigung": 2,
    "loecher": {
        "gremien": false,
        "sp": false
    },
    "nummer": 1217539,
    "semester": "Wintersemester 2017/2018",
    "stud": {
        "ausweistyp": "regulaer",
        "beurlaubt": false,
        "fakultaet": 4,
        "geburtsdatum": "08.04.1990",
        "matrikelnummer": 2838875,
        "mehrfachausfertigung": 2,
        "mitglied_studierendenschaft": true,
        "nachname": "Herber",
        "plzort": "53138 Bonn",
        "sternchen": 0,
        "strasse": "Gilbrechtstra\u00dfe 16",
        "studienfaecher": [
            {
                "abschluss": "Med.Doc/Doc.of Philosophy",
                "fach": "Klinische Medizin",
                "fsem": 9
            }
        ],
        "vorname": "Apollonia",
        "weiblich": true
    }
}
