{
    "ausfertigung": 2,
    "loecher": {
        "gremien": false,
        "sp": false
    },
    "nummer": 2463237,
    "semester": "Wintersemester 2016/2017",
    "stud": {
        "beurlaubt": false,
        "fakultaet": 3,
        "geburtsdatum": "15.05.1990",
        "matrikelnummer": 2426241,
        "mehrfachausfertigung": 2,
        "nachname": "Friebe",
        "plzort": "53139 Bonn",
        "sternchen": 0,
        "strasse": "An der Steinm\u00fchle 6",
        "studienfaecher": [
            {
                "abschluss": "Master of Disaster",
                "fach": "Katastrophenmanagement",
                "fsem": 0
            }
        ],
        "vorname": "Frankmut",
        "weiblich": false
    }
}
