{
    "ausfertigung": 1,
    "loecher": {
        "gremien": false,
        "sp": false
    },
    "nummer": 2235708,
    "semester": "Wintersemester 2016/2017",
    "stud": {
        "beurlaubt": false,
        "fakultaet": 6,
        "geburtsdatum": "21.12.1991",
        "matrikelnummer": 145956,
        "mehrfachausfertigung": 1,
        "nachname": "Fleischhauer",
        "plzort": "17291 Sch\u00f6nfeld",
        "sternchen": 0,
        "strasse": "T\u00f6plitzstra\u00dfe 9c",
        "studienfaecher": [
            {
                "abschluss": "Master of Disaster",
                "fach": "Katastrophenmanagement",
                "fsem": 0
            }
        ],
        "vorname": "Kai",
        "weiblich": false
    }
}
