{
    "ausfertigung": 3,
    "loecher": {
        "gremien": false,
        "sp": false
    },
    "nummer": 1873069,
    "semester": "Wintersemester 2016/2017",
    "stud": {
        "beurlaubt": false,
        "fakultaet": 7,
        "geburtsdatum": "23.09.1992",
        "matrikelnummer": 2710387,
        "mehrfachausfertigung": 4,
        "nachname": "Thum",
        "plzort": "53182 Bonn",
        "sternchen": 0,
        "strasse": "Steinbruchweg 8a",
        "studienfaecher": [
            {
                "abschluss": "Master of Disaster",
                "fach": "Katastrophenmanagement",
                "fsem": 0
            }
        ],
        "vorname": "Alheide",
        "weiblich": true
    }
}
