{
    "ausfertigung": 1,
    "loecher": {
        "gremien": false,
        "sp": false
    },
    "nummer": 2770768,
    "semester": "Wintersemester 2016/2017",
    "stud": {
        "ausweistyp": "regulaer",
        "beurlaubt": false,
        "fakultaet": 6,
        "geburtsdatum": "28.04.1994",
        "matrikelnummer": 2699161,
        "mehrfachausfertigung": 1,
        "mitglied_studierendenschaft": true,
        "nachname": "Eibl",
        "plzort": "53186 Bonn",
        "sternchen": 0,
        "strasse": "Br\u00fchlsche Gasse 1",
        "studienfaecher": [
            {
                "abschluss": "Master of Disaster",
                "fach": "Katastrophenmanagement",
                "fsem": 0
            }
        ],
        "vorname": "Kathy",
        "weiblich": true
    }
}
