{
    "ausfertigung": 1,
    "loecher": {
        "gremien": false,
        "sp": false
    },
    "nummer": 1082893,
    "semester": "Wintersemester 2017/2018",
    "stud": {
        "ausweistyp": "regulaer",
        "beurlaubt": false,
        "fakultaet": 8,
        "geburtsdatum": "10.10.1996",
        "matrikelnummer": 3033771,
        "mehrfachausfertigung": 1,
        "mitglied_studierendenschaft": true,
        "nachname": "H\u00f6ft",
        "plzort": "53225 Bonn",
        "sternchen": 0,
        "strasse": "Breslauer Stra\u00dfe 5",
        "studienfaecher": [
            {
                "abschluss": "LA BA Gym Ge",
                "fach": "Biologie",
                "fsem": 5
            },
            {
                "abschluss": "",
                "fach": "Latein",
                "fsem": 5
            },
            {
                "abschluss": "",
                "fach": "Bildungswissenschaften",
                "fsem": 5
            }
        ],
        "vorname": "Ingram",
        "weiblich": false
    }
}
