{
    "ausfertigung": 1,
    "loecher": {
        "gremien": false,
        "sp": false
    },
    "nummer": 1097299,
    "semester": "Wintersemester 2016/2017",
    "stud": {
        "beurlaubt": false,
        "fakultaet": 6,
        "geburtsdatum": "02.01.1993",
        "matrikelnummer": 119760,
        "mehrfachausfertigung": 1,
        "nachname": "Tesch",
        "plzort": "53131 Bonn",
        "sternchen": 0,
        "strasse": "Walter-Schwagenscheidt-Platz 36e",
        "studienfaecher": [
            {
                "abschluss": "Master of Disaster",
                "fach": "Katastrophenmanagement",
                "fsem": 0
            }
        ],
        "vorname": "Silvia",
        "weiblich": true
    }
}
