{
    "ausfertigung": 1,
    "loecher": {
        "gremien": false,
        "sp": false
    },
    "nummer": 1467982,
    "semester": "Wintersemester 2016/2017",
    "stud": {
        "ausweistyp": "weiterbildung",
        "beurlaubt": false,
        "fakultaet": 6,
        "geburtsdatum": "13.02.1993",
        "matrikelnummer": 12503,
        "mehrfachausfertigung": 1,
        "mitglied_studierendenschaft": true,
        "nachname": "Oehme",
        "plzort": "7",
        "sternchen": 0,
        "strasse": "Platanenallee 15",
        "studienfaecher": [
            {
                "abschluss": "Master of Disaster",
                "fach": "Katastrophenmanagement",
                "fsem": 0
            }
        ],
        "vorname": "Ignatz",
        "weiblich": false
    }
}
