{
    "ausfertigung": 1,
    "loecher": {
        "gremien": false,
        "sp": false
    },
    "nummer": 1378001,
    "semester": "Wintersemester 2016/2017",
    "stud": {
        "beurlaubt": true,
        "fakultaet": 3,
        "geburtsdatum": "09.02.1991",
        "matrikelnummer": 2263155,
        "mehrfachausfertigung": 1,
        "nachname": "Heimann",
        "plzort": "17268 Grunewald",
        "sternchen": 0,
        "strasse": "Maternistra\u00dfe 30",
        "studienfaecher": [
            {
                "abschluss": "Master of Disaster",
                "fach": "Katastrophenmanagement",
                "fsem": 0
            }
        ],
        "vorname": "Erltrud",
        "weiblich": true
    }
}
