{
    "ausfertigung": 1,
    "loecher": {
        "gremien": false,
        "sp": false
    },
    "nummer": 1689198,
    "semester": "Wintersemester 2018/2019",
    "stud": {
        "ausweistyp": "regulaer",
        "beurlaubt": false,
        "fakultaet": 4,
        "geburtsdatum": "11.09.1990",
        "matrikelnummer": 2838660,
        "mehrfachausfertigung": 1,
        "mitglied_studierendenschaft": true,
        "nachname": "Harder",
        "plzort": "53225 Bonn",
        "sternchen": 0,
        "strasse": "Im Klingenfeld 10",
        "studienfaecher": [
            {
                "abschluss": "Promotion",
                "fach": "Zahnmedizin",
                "fsem": 10
            }
        ],
        "vorname": "Regina",
        "weiblich": true
    }
}
