{
    "ausfertigung": 5,
    "loecher": {
        "gremien": false,
        "sp": false
    },
    "nummer": 1939876,
    "semester": "Wintersemester 2016/2017",
    "stud": {
        "beurlaubt": false,
        "fakultaet": 5,
        "geburtsdatum": "01.01.1992",
        "matrikelnummer": 2488689,
        "mehrfachausfertigung": 5,
        "nachname": "Hauschild",
        "plzort": "53202 Bonn",
        "sternchen": 0,
        "strasse": "Rohrkolbenstieg 1c",
        "studienfaecher": [
            {
                "abschluss": "Master of Disaster",
                "fach": "Katastrophenmanagement",
                "fsem": 0
            }
        ],
        "vorname": "Nicolaus",
        "weiblich": false
    }
}
