{
    "ausfertigung": 1,
    "loecher": {
        "gremien": false,
        "sp": false
    },
    "nummer": 1876060,
    "semester": "Wintersemester 2017/2018",
    "stud": {
        "ausweistyp": "regulaer",
        "beurlaubt": false,
        "fakultaet": 6,
        "geburtsdatum": "23.07.1996",
        "matrikelnummer": 126023,
        "mehrfachausfertigung": 1,
        "mitglied_studierendenschaft": true,
        "nachname": "Gebauer",
        "plzort": "53149 Bonn",
        "sternchen": 0,
        "strasse": "Glitzaweg 4",
        "studienfaecher": [
            {
                "abschluss": "Master of Science",
                "fach": "Life and Medical Sciences",
                "fsem": 12
            }
        ],
        "vorname": "Ruthilde",
        "weiblich": true
    }
}
