{
    "ausfertigung": 1,
    "loecher": {
        "gremien": false,
        "sp": false
    },
    "nummer": 1630350,
    "semester": "Wintersemester 2017/2018",
    "stud": {
        "ausweistyp": "regulaer",
        "beurlaubt": false,
        "fakultaet": 3,
        "geburtsdatum": "20.02.1992",
        "matrikelnummer": 2519713,
        "mehrfachausfertigung": 1,
        "mitglied_studierendenschaft": true,
        "nachname": "Steigerwald",
        "plzort": "15926 Luckau",
        "sternchen": 0,
        "strasse": "Hauptwachstr. 4",
        "studienfaecher": [
            {
                "abschluss": "Staatsex.",
                "fach": "Rechtswissenschaft",
                "fsem": 10
            }
        ],
        "vorname": "Werner",
        "weiblich": false
    }
}
