{
    "ausfertigung": 2,
    "loecher": {
        "gremien": false,
        "sp": false
    },
    "nummer": 2974937,
    "semester": "Wintersemester 2016/2017",
    "stud": {
        "beurlaubt": false,
        "fakultaet": 8,
        "geburtsdatum": "28.06.1986",
        "matrikelnummer": 2044343,
        "mehrfachausfertigung": 2,
        "nachname": "R\u00fcther",
        "plzort": "53182 Bonn",
        "sternchen": 0,
        "strasse": "Mu\u00dfstr. 35",
        "studienfaecher": [
            {
                "abschluss": "Master of Disaster",
                "fach": "Katastrophenmanagement",
                "fsem": 0
            }
        ],
        "vorname": "Eitelbert",
        "weiblich": false
    }
}
