{
    "ausfertigung": 1,
    "loecher": {
        "gremien": false,
        "sp": false
    },
    "nummer": 1270215,
    "semester": "Wintersemester 2016/2017",
    "stud": {
        "beurlaubt": false,
        "fakultaet": 6,
        "geburtsdatum": "05.11.1989",
        "matrikelnummer": 17274,
        "mehrfachausfertigung": 1,
        "nachname": "Loibl",
        "plzort": "53229 Bonn",
        "sternchen": 0,
        "strasse": "F\u00fcrstenallee 5",
        "studienfaecher": [
            {
                "abschluss": "Master of Disaster",
                "fach": "Katastrophenmanagement",
                "fsem": 0
            }
        ],
        "vorname": "Veronica",
        "weiblich": true
    }
}
