{
    "ausfertigung": 1,
    "loecher": {
        "gremien": false,
        "sp": false
    },
    "nummer": 1724372,
    "semester": "Wintersemester 2016/2017",
    "stud": {
        "beurlaubt": false,
        "fakultaet": 6,
        "geburtsdatum": "09.01.1987",
        "matrikelnummer": 1952874,
        "mehrfachausfertigung": 1,
        "nachname": "Gerke",
        "plzort": "17419 Zirchow",
        "sternchen": 0,
        "strasse": "Zum Nixenteich 3",
        "studienfaecher": [
            {
                "abschluss": "Master of Disaster",
                "fach": "Katastrophenmanagement",
                "fsem": 0
            }
        ],
        "vorname": "Erlfried",
        "weiblich": false
    }
}
