{
    "ausfertigung": 1,
    "loecher": {
        "gremien": true,
        "sp": true
    },
    "nummer": 2664571,
    "semester": "Wintersemester 2016/2017",
    "stud": {
        "ausweistyp": "regulaer",
        "beurlaubt": false,
        "fakultaet": 6,
        "geburtsdatum": "14.03.1990",
        "matrikelnummer": 2471475,
        "mehrfachausfertigung": 1,
        "mitglied_studierendenschaft": true,
        "nachname": "Fritzsch",
        "plzort": "53228 Bonn",
        "sternchen": 0,
        "strasse": "Frutolfstr. 0",
        "studienfaecher": [
            {
                "abschluss": "Bachelor of Science",
                "fach": "Geographie",
                "fsem": 12
            }
        ],
        "vorname": "Herwart",
        "weiblich": false
    }
}
