{
    "ausfertigung": 1,
    "loecher": {
        "gremien": false,
        "sp": false
    },
    "nummer": 2870531,
    "semester": "Wintersemester 2016/2017",
    "stud": {
        "beurlaubt": true,
        "fakultaet": 3,
        "geburtsdatum": "04.02.1989",
        "matrikelnummer": 2527194,
        "mehrfachausfertigung": 1,
        "nachname": "Tietz",
        "plzort": "89231 Neu-Ulm",
        "sternchen": 0,
        "strasse": "Barkhausenstra\u00dfe 3",
        "studienfaecher": [
            {
                "abschluss": "Master of Disaster",
                "fach": "Katastrophenmanagement",
                "fsem": 0
            }
        ],
        "vorname": "Heidelinde",
        "weiblich": true
    }
}
