{
    "ausfertigung": 1,
    "loecher": {
        "gremien": false,
        "sp": false
    },
    "nummer": 2504857,
    "semester": "Wintersemester 2017/2018",
    "stud": {
        "ausweistyp": "regulaer",
        "beurlaubt": false,
        "fakultaet": 1,
        "geburtsdatum": "05.07.1993",
        "matrikelnummer": 2425100,
        "mehrfachausfertigung": 1,
        "mitglied_studierendenschaft": true,
        "nachname": "Pfister",
        "plzort": "89440 Lutzingen",
        "sternchen": 0,
        "strasse": "Friedrich-Adolph-Sorge-Stra\u00dfe 4d",
        "studienfaecher": [
            {
                "abschluss": "Magister Theologiae (kath.)",
                "fach": "Katholische Theologie",
                "fsem": 8
            }
        ],
        "vorname": "Ehrentraud",
        "weiblich": true
    }
}
