{
    "ausfertigung": 2,
    "loecher": {
        "gremien": false,
        "sp": false
    },
    "nummer": 1844597,
    "semester": "Sommersemester 2016",
    "stud": {
        "ausweistyp": "regulaer",
        "beurlaubt": false,
        "fakultaet": 3,
        "geburtsdatum": "04.01.1991",
        "matrikelnummer": 2870231,
        "mehrfachausfertigung": 2,
        "mitglied_studierendenschaft": true,
        "nachname": "Kistner",
        "plzort": "53145 Bonn",
        "sternchen": 0,
        "strasse": "Am Promigberg 3",
        "studienfaecher": [
            {
                "abschluss": "Master of Disaster",
                "fach": "Katastrophenmanagement",
                "fsem": 0
            }
        ],
        "vorname": "Meinolf",
        "weiblich": false
    }
}
