{
    "ausfertigung": 1,
    "loecher": {
        "gremien": true,
        "sp": true
    },
    "nummer": 2680499,
    "semester": "Wintersemester 2016/2017",
    "stud": {
        "beurlaubt": false,
        "fakultaet": 7,
        "geburtsdatum": "24.10.1995",
        "matrikelnummer": 16483,
        "mehrfachausfertigung": 1,
        "nachname": "Pauls",
        "plzort": "86688 Marxheim",
        "sternchen": 0,
        "strasse": "Lupinenkamp 2",
        "studienfaecher": [
            {
                "abschluss": "Master of Disaster",
                "fach": "Katastrophenmanagement",
                "fsem": 0
            }
        ],
        "vorname": "Ulvi",
        "weiblich": false
    }
}
