{
    "ausfertigung": 1,
    "loecher": {
        "gremien": false,
        "sp": false
    },
    "nummer": 1436890,
    "semester": "Wintersemester 2017/2018",
    "stud": {
        "ausweistyp": "regulaer",
        "beurlaubt": false,
        "fakultaet": 8,
        "geburtsdatum": "05.02.1991",
        "matrikelnummer": 18407,
        "mehrfachausfertigung": 1,
        "mitglied_studierendenschaft": true,
        "nachname": "Scheid",
        "plzort": "53182 Bonn",
        "sternchen": 0,
        "strasse": "Erste Banksbr\u00fccke 0",
        "studienfaecher": [
            {
                "abschluss": "LA MA Berufskolleg",
                "fach": "Tierwissenschaften (Tierhaltung)",
                "fsem": 7
            },
            {
                "abschluss": "",
                "fach": "Lebensmitteltechnologie (Lebensmitteltechnik)",
                "fsem": 7
            },
            {
                "abschluss": "",
                "fach": "Bildungswissenschaften",
                "fsem": 7
            }
        ],
        "vorname": "Adelhard",
        "weiblich": false
    }
}
