{
    "ausfertigung": 1,
    "loecher": {
        "gremien": false,
        "sp": false
    },
    "nummer": 1137897,
    "semester": "Wintersemester 2016/2017",
    "stud": {
        "ausweistyp": "regulaer",
        "beurlaubt": false,
        "fakultaet": 5,
        "geburtsdatum": "08.07.1999",
        "matrikelnummer": 15574,
        "mehrfachausfertigung": 1,
        "mitglied_studierendenschaft": true,
        "nachname": "Dreher",
        "plzort": "56753 Mertloch",
        "sternchen": 0,
        "strasse": "Rosentalried 2",
        "studienfaecher": [
            {
                "abschluss": "Master of Arts",
                "fach": "Kulturstudien zu Lateinamerika/Estudios culturales de America Latina",
                "fsem": 12
            }
        ],
        "vorname": "Hasko",
        "weiblich": false
    }
}
