{
    "ausfertigung": 1,
    "loecher": {
        "gremien": false,
        "sp": false
    },
    "nummer": 2146927,
    "semester": "Wintersemester 2016/2017",
    "stud": {
        "beurlaubt": false,
        "fakultaet": 7,
        "geburtsdatum": "24.09.1998",
        "matrikelnummer": 2346860,
        "mehrfachausfertigung": 1,
        "nachname": "Abraham",
        "plzort": "53195 Bonn",
        "sternchen": 0,
        "strasse": "Meisenweg 16",
        "studienfaecher": [
            {
                "abschluss": "Master of Disaster",
                "fach": "Katastrophenmanagement",
                "fsem": 0
            }
        ],
        "vorname": "Steffan",
        "weiblich": false
    }
}
