{
    "ausfertigung": 1,
    "loecher": {
        "gremien": false,
        "sp": false
    },
    "nummer": 1970385,
    "semester": "Wintersemester 2016/2017",
    "stud": {
        "beurlaubt": false,
        "fakultaet": 6,
        "geburtsdatum": "21.10.1991",
        "matrikelnummer": 1939207,
        "mehrfachausfertigung": 1,
        "nachname": "Fritsch",
        "plzort": "63697 Hirzenhain",
        "sternchen": 0,
        "strasse": "Anspacher Stra\u00dfe 23",
        "studienfaecher": [
            {
                "abschluss": "Master of Disaster",
                "fach": "Katastrophenmanagement",
                "fsem": 0
            }
        ],
        "vorname": "Tiburtius",
        "weiblich": false
    }
}
