{
    "ausfertigung": 1,
    "loecher": {
        "gremien": false,
        "sp": false
    },
    "nummer": 1779213,
    "semester": "Wintersemester 2016/2017",
    "stud": {
        "ausweistyp": "regulaer",
        "beurlaubt": false,
        "fakultaet": 4,
        "geburtsdatum": "16.01.1999",
        "matrikelnummer": 3114071,
        "mehrfachausfertigung": 1,
        "mitglied_studierendenschaft": true,
        "nachname": "Teubner",
        "plzort": "53191 Bonn",
        "sternchen": 0,
        "strasse": "Wilhelmstra\u00dfe 22",
        "studienfaecher": [
            {
                "abschluss": "Staatsex.",
                "fach": "Medizin",
                "fsem": 1
            },
            {
                "abschluss": "Bachelor of Arts",
                "fach": "Evangelische Theologie und Hermeneutik",
                "fsem": 13
            }
        ],
        "vorname": "Christhelm",
        "weiblich": false
    }
}
