{
    "ausfertigung": 1,
    "loecher": {
        "gremien": false,
        "sp": false
    },
    "nummer": 2564093,
    "semester": "Wintersemester 2016/2017",
    "stud": {
        "beurlaubt": false,
        "fakultaet": 7,
        "geburtsdatum": "03.02.1993",
        "matrikelnummer": 2665400,
        "mehrfachausfertigung": 1,
        "nachname": "Kretschmer",
        "plzort": "53194 Bonn",
        "sternchen": 0,
        "strasse": "Beim Wilden Schwein 27",
        "studienfaecher": [
            {
                "abschluss": "Master of Disaster",
                "fach": "Katastrophenmanagement",
                "fsem": 0
            }
        ],
        "vorname": "Johannette",
        "weiblich": true
    }
}
