{
    "ausfertigung": 1,
    "loecher": {
        "gremien": false,
        "sp": false
    },
    "nummer": 1831295,
    "semester": "Wintersemester 2018/2019",
    "stud": {
        "ausweistyp": "regulaer",
        "beurlaubt": false,
        "fakultaet": 2,
        "geburtsdatum": "03.09.1995",
        "matrikelnummer": 2811372,
        "mehrfachausfertigung": 1,
        "mitglied_studierendenschaft": true,
        "nachname": "Meise",
        "plzort": "45897 Gelsenkirchen",
        "sternchen": 0,
        "strasse": "Heiligenh\u00e4usel 1b",
        "studienfaecher": [
            {
                "abschluss": "Kirchl.Ex.",
                "fach": "Evangelische Theologie",
                "fsem": 10
            }
        ],
        "vorname": "Burkhart",
        "weiblich": false
    }
}
