{
    "ausfertigung": 2,
    "loecher": {
        "gremien": false,
        "sp": false
    },
    "nummer": 2838471,
    "semester": "Wintersemester 2016/2017",
    "stud": {
        "beurlaubt": false,
        "fakultaet": 8,
        "geburtsdatum": "18.07.1998",
        "matrikelnummer": 2921934,
        "mehrfachausfertigung": 2,
        "nachname": "H\u00fcls",
        "plzort": "53227 Bonn",
        "sternchen": 0,
        "strasse": "J\u00e4gergasse 8",
        "studienfaecher": [
            {
                "abschluss": "Master of Disaster",
                "fach": "Katastrophenmanagement",
                "fsem": 0
            }
        ],
        "vorname": "Niklas",
        "weiblich": false
    }
}
