{
    "ausfertigung": 1,
    "loecher": {
        "gremien": false,
        "sp": true
    },
    "nummer": 2198826,
    "semester": "Wintersemester 2016/2017",
    "stud": {
        "beurlaubt": false,
        "fakultaet": 6,
        "geburtsdatum": "01.03.1991",
        "matrikelnummer": 13977,
        "mehrfachausfertigung": 1,
        "nachname": "Liese",
        "plzort": "17209 Wredenhagen",
        "sternchen": 0,
        "strasse": "Nachtfl\u00fcgelweg 0",
        "studienfaecher": [
            {
                "abschluss": "Master of Disaster",
                "fach": "Katastrophenmanagement",
                "fsem": 0
            }
        ],
        "vorname": "Marfried",
        "weiblich": false
    }
}
