{
    "ausfertigung": 3,
    "loecher": {
        "gremien": false,
        "sp": false
    },
    "nummer": 1399252,
    "semester": "Wintersemester 2017/2018",
    "stud": {
        "ausweistyp": "regulaer",
        "beurlaubt": false,
        "fakultaet": 9,
        "geburtsdatum": "16.09.1988",
        "matrikelnummer": 2413267,
        "mehrfachausfertigung": 5,
        "mitglied_studierendenschaft": true,
        "nachname": "Schreck",
        "plzort": "53201 Bonn",
        "sternchen": 0,
        "strasse": "Schultzweg 0",
        "studienfaecher": [
            {
                "abschluss": "Promotion",
                "fach": "Volkswirtschaftslehre",
                "fsem": 3
            }
        ],
        "vorname": "Holm",
        "weiblich": false
    }
}
