{
    "ausfertigung": 1,
    "loecher": {
        "gremien": false,
        "sp": false
    },
    "nummer": 1822836,
    "semester": "Wintersemester 2016/2017",
    "stud": {
        "beurlaubt": false,
        "fakultaet": 6,
        "geburtsdatum": "18.04.1988",
        "matrikelnummer": 2153412,
        "mehrfachausfertigung": 1,
        "nachname": "Bohr",
        "plzort": "53145 Bonn",
        "sternchen": 0,
        "strasse": "Lohoffstra\u00dfe 1",
        "studienfaecher": [
            {
                "abschluss": "Master of Disaster",
                "fach": "Katastrophenmanagement",
                "fsem": 0
            }
        ],
        "vorname": "Thekla",
        "weiblich": true
    }
}
