{
    "ausfertigung": 1,
    "loecher": {
        "gremien": false,
        "sp": false
    },
    "nummer": 2290861,
    "semester": "Wintersemester 2016/2017",
    "stud": {
        "ausweistyp": "regulaer",
        "beurlaubt": false,
        "fakultaet": 9,
        "geburtsdatum": "06.10.1999",
        "matrikelnummer": 145503,
        "mehrfachausfertigung": 1,
        "mitglied_studierendenschaft": true,
        "nachname": "Lambertz",
        "plzort": "53186 Bonn",
        "sternchen": 0,
        "strasse": "Ruster Stra\u00dfe 2",
        "studienfaecher": [
            {
                "abschluss": "Master of Science",
                "fach": "Economics",
                "fsem": 12
            }
        ],
        "vorname": "Anneliese",
        "weiblich": true
    }
}
