{
    "ausfertigung": 1,
    "loecher": {
        "gremien": true,
        "sp": true
    },
    "nummer": 1013010,
    "semester": "Wintersemester 2017/2018",
    "stud": {
        "ausweistyp": "weiterbildung",
        "beurlaubt": false,
        "fakultaet": 2,
        "geburtsdatum": "11.09.1986",
        "matrikelnummer": 191668,
        "mehrfachausfertigung": 1,
        "mitglied_studierendenschaft": false,
        "nachname": "Paul",
        "plzort": "25927 Neukirchen",
        "sternchen": 0,
        "strasse": "Heiligkreuzgasse 0",
        "studienfaecher": [
            {
                "abschluss": "Magister Theologiae (ev.)",
                "fach": "Evangelische Theologie",
                "fsem": 9
            }
        ],
        "vorname": "Jannick",
        "weiblich": false
    }
}
