{
    "ausfertigung": 1,
    "loecher": {
        "gremien": false,
        "sp": false
    },
    "nummer": "00000000",
    "semester": "Sommersemester 2016",
    "stud": {
        "fakultaet": 5,
        "geburtsdatum": "27.05.1999",
        "matrikelnummer": 2740539,
        "mehrfachausfertigung": 1,
        "nachname": "Eberle",
        "plzort": "53127 Bonn",
        "sternchen": 0,
        "strasse": "Winterhuder Weg 19",
        "studienfaecher": [
            {
                "abschluss": "Master of Disaster",
                "fach": "Katastrophenmanagement",
                "fsem": 0
            }
        ],
        "vorname": "Francoise",
        "weiblich": true
    }
}
