{
    "ausfertigung": 5,
    "loecher": {
        "gremien": true,
        "sp": true
    },
    "nummer": 2250004,
    "semester": "Wintersemester 2017/2018",
    "stud": {
        "ausweistyp": "regulaer",
        "beurlaubt": false,
        "fakultaet": 8,
        "geburtsdatum": "04.05.1994",
        "matrikelnummer": 17551,
        "mehrfachausfertigung": 5,
        "mitglied_studierendenschaft": true,
        "nachname": "Weiland",
        "plzort": "53154 Bonn",
        "sternchen": 0,
        "strasse": "Zum-Jungen-Stra\u00dfe 2b",
        "studienfaecher": [
            {
                "abschluss": "LA BA Berufskolleg",
                "fach": "Agrarwissenschaft",
                "fsem": 11
            },
            {
                "abschluss": "",
                "fach": "Lebensmitteltechnologie (Lebensmitteltechnik)",
                "fsem": 11
            },
            {
                "abschluss": "",
                "fach": "Bildungswissenschaften",
                "fsem": 11
            },
            {
                "abschluss": "Master of Science",
                "fach": "Life Science Informatics",
                "fsem": 11
            }
        ],
        "vorname": "Katharina",
        "weiblich": true
    }
}
