{
    "ausfertigung": 1,
    "loecher": {
        "gremien": false,
        "sp": false
    },
    "nummer": 2558946,
    "semester": "Wintersemester 2017/2018",
    "stud": {
        "ausweistyp": "regulaer",
        "beurlaubt": false,
        "fakultaet": 6,
        "geburtsdatum": "18.09.1984",
        "matrikelnummer": 2453033,
        "mehrfachausfertigung": 1,
        "mitglied_studierendenschaft": true,
        "nachname": "Pietschmann",
        "plzort": "53184 Bonn",
        "sternchen": 0,
        "strasse": "Justinuskirchstra\u00dfe 19",
        "studienfaecher": [
            {
                "abschluss": "Promotion",
                "fach": "Astronomie/Astrophysik",
                "fsem": 6
            }
        ],
        "vorname": "Kathrin",
        "weiblich": true
    }
}
