{
    "ausfertigung": 2,
    "loecher": {
        "gremien": false,
        "sp": false
    },
    "nummer": 2847465,
    "semester": "Wintersemester 2016/2017",
    "stud": {
        "beurlaubt": false,
        "fakultaet": 5,
        "geburtsdatum": "06.02.1990",
        "matrikelnummer": 2775573,
        "mehrfachausfertigung": 2,
        "nachname": "M\u00fcnz",
        "plzort": "53179 Bonn",
        "sternchen": 0,
        "strasse": "S\u00f6mmerringstra\u00dfe 36",
        "studienfaecher": [
            {
                "abschluss": "Master of Disaster",
                "fach": "Katastrophenmanagement",
                "fsem": 0
            }
        ],
        "vorname": "Sighilde",
        "weiblich": true
    }
}
