{
    "ausfertigung": 2,
    "loecher": {
        "gremien": false,
        "sp": false
    },
    "nummer": 1829261,
    "semester": "Wintersemester 2016/2017",
    "stud": {
        "beurlaubt": true,
        "fakultaet": 6,
        "geburtsdatum": "16.11.1994",
        "matrikelnummer": 2059141,
        "mehrfachausfertigung": 2,
        "nachname": "Heese",
        "plzort": "53120 Bonn",
        "sternchen": 0,
        "strasse": "Fabriciusstra\u00dfe 7",
        "studienfaecher": [
            {
                "abschluss": "Master of Disaster",
                "fach": "Katastrophenmanagement",
                "fsem": 0
            }
        ],
        "vorname": "Margareth",
        "weiblich": true
    }
}
