{
    "ausfertigung": 1,
    "loecher": {
        "gremien": false,
        "sp": false
    },
    "nummer": 2352046,
    "semester": "Wintersemester 2018/2019",
    "stud": {
        "ausweistyp": "zweithoerer",
        "beurlaubt": false,
        "fakultaet": 6,
        "geburtsdatum": "21.01.1984",
        "matrikelnummer": 2297718,
        "mehrfachausfertigung": 1,
        "mitglied_studierendenschaft": true,
        "nachname": "Hohn",
        "plzort": "53218 Bonn",
        "sternchen": 0,
        "strasse": "Seckbacher Bitzweg 20",
        "studienfaecher": [
            {
                "abschluss": "Master of Science",
                "fach": "Chemistry",
                "fsem": 2
            },
            {
                "abschluss": "Master of Science",
                "fach": "Economics",
                "fsem": 2
            }
        ],
        "vorname": "Till",
        "weiblich": false
    }
}
