{
    "ausfertigung": 1,
    "loecher": {
        "gremien": false,
        "sp": false
    },
    "nummer": 2006522,
    "semester": "Sommersemester 2017",
    "stud": {
        "ausweistyp": "zweithoerer",
        "beurlaubt": false,
        "fakultaet": 4,
        "geburtsdatum": "10.10.1992",
        "matrikelnummer": 2819449,
        "mehrfachausfertigung": 1,
        "mitglied_studierendenschaft": true,
        "nachname": "Zemantek",
        "plzort": "53216 Bonn",
        "sternchen": 0,
        "strasse": "Hans-J\u00fcchser-Stra\u00dfe 32",
        "studienfaecher": [
            {
                "abschluss": "Staatsex.",
                "fach": "Zahnmedizin",
                "fsem": 7
            }
        ],
        "vorname": "Sven",
        "weiblich": true
    }
}
