{
    "ausfertigung": 1,
    "loecher": {
        "gremien": false,
        "sp": false
    },
    "nummer": 2702172,
    "semester": "Wintersemester 2018/2019",
    "stud": {
        "ausweistyp": "zweithoerer",
        "beurlaubt": true,
        "fakultaet": 9,
        "geburtsdatum": "24.04.1995",
        "matrikelnummer": 2102062,
        "mehrfachausfertigung": 1,
        "mitglied_studierendenschaft": true,
        "nachname": "Pesch",
        "plzort": "53188 Bonn",
        "sternchen": 0,
        "strasse": "Meinhardtweg 2",
        "studienfaecher": [
            {
                "abschluss": "Promotion",
                "fach": "Volkswirtschaftslehre",
                "fsem": 7
            }
        ],
        "vorname": "Mirko",
        "weiblich": false
    }
}
