{
    "ausfertigung": 1,
    "loecher": {
        "gremien": true,
        "sp": true
    },
    "nummer": 1969322,
    "semester": "Wintersemester 2017/2018",
    "stud": {
        "ausweistyp": "regulaer",
        "beurlaubt": false,
        "fakultaet": 6,
        "geburtsdatum": "28.05.1995",
        "matrikelnummer": 2519409,
        "mehrfachausfertigung": 1,
        "mitglied_studierendenschaft": true,
        "nachname": "Balzer",
        "plzort": "96352 Wilhelmsthal",
        "sternchen": 0,
        "strasse": "Kirchlinden 4",
        "studienfaecher": [
            {
                "abschluss": "Master of Science",
                "fach": "Biochemistry",
                "fsem": 5
            }
        ],
        "vorname": "Dorle",
        "weiblich": true
    }
}
