{
    "ausfertigung": 3,
    "loecher": {
        "gremien": false,
        "sp": false
    },
    "nummer": 2679814,
    "semester": "Wintersemester 2016/2017",
    "stud": {
        "ausweistyp": "regulaer",
        "beurlaubt": false,
        "fakultaet": 6,
        "geburtsdatum": "03.10.1994",
        "matrikelnummer": 176914,
        "mehrfachausfertigung": 3,
        "mitglied_studierendenschaft": true,
        "nachname": "B\u00f6hringer",
        "plzort": "53143 Bonn",
        "sternchen": 0,
        "strasse": "Gartenheimallee 0",
        "studienfaecher": [
            {
                "abschluss": "Promotion",
                "fach": "Mathematik",
                "fsem": 13
            }
        ],
        "vorname": "Sina",
        "weiblich": true
    }
}
