{
    "ausfertigung": 1,
    "loecher": {
        "gremien": false,
        "sp": false
    },
    "nummer": 1365547,
    "semester": "Wintersemester 2017/2018",
    "stud": {
        "ausweistyp": "regulaer",
        "beurlaubt": false,
        "fakultaet": 0,
        "geburtsdatum": "12.02.1989",
        "matrikelnummer": 2500811,
        "mehrfachausfertigung": 1,
        "mitglied_studierendenschaft": true,
        "nachname": "Wollschl\u00e4ger",
        "plzort": "53141 Bonn",
        "sternchen": 0,
        "strasse": "Caumannsstra\u00dfe 3",
        "studienfaecher": [
            {
                "abschluss": "Promotion",
                "fach": "Entwicklungsforschung",
                "fsem": 10
            }
        ],
        "vorname": "Winrich",
        "weiblich": false
    }
}
