{
    "ausfertigung": 1,
    "loecher": {
        "gremien": false,
        "sp": false
    },
    "nummer": 1675152,
    "semester": "Wintersemester 2016/2017",
    "stud": {
        "ausweistyp": "zweithoerer",
        "beurlaubt": false,
        "fakultaet": 3,
        "geburtsdatum": "21.08.1990",
        "matrikelnummer": 2858177,
        "mehrfachausfertigung": 1,
        "mitglied_studierendenschaft": true,
        "nachname": "Jochum",
        "plzort": "53167 Bonn",
        "sternchen": 0,
        "strasse": "Fischadlerstieg 9",
        "studienfaecher": [
            {
                "abschluss": "Bachelor of Arts",
                "fach": "Begleitfach Rechtswissenschaft",
                "fsem": 13
            },
            {
                "abschluss": "Staatsex.",
                "fach": "Lebensmittelchemie",
                "fsem": 7
            }
        ],
        "vorname": "Sigmund",
        "weiblich": false
    }
}
