{
    "ausfertigung": 1,
    "loecher": {
        "gremien": true,
        "sp": false
    },
    "nummer": 1044633,
    "semester": "Wintersemester 2017/2018",
    "stud": {
        "ausweistyp": "regulaer",
        "beurlaubt": false,
        "fakultaet": 4,
        "geburtsdatum": "09.05.1996",
        "matrikelnummer": 2554538,
        "mehrfachausfertigung": 1,
        "mitglied_studierendenschaft": true,
        "nachname": "Hundertmark",
        "plzort": "57612 Birnbach",
        "sternchen": 0,
        "strasse": "Am Steinbruch 10",
        "studienfaecher": [
            {
                "abschluss": "Master",
                "fach": "Klinische Medizintechnik",
                "fsem": 5
            }
        ],
        "vorname": "Siggi",
        "weiblich": true
    }
}
