{
    "ausfertigung": 3,
    "loecher": {
        "gremien": true,
        "sp": true
    },
    "nummer": 2101605,
    "semester": "Wintersemester 2016/2017",
    "stud": {
        "beurlaubt": false,
        "fakultaet": 2,
        "geburtsdatum": "01.03.1997",
        "matrikelnummer": 147642,
        "mehrfachausfertigung": 3,
        "nachname": "Kr\u00f6ll",
        "plzort": "53116 Bonn",
        "sternchen": 0,
        "strasse": "R\u00f6hrhofsgasse 15b",
        "studienfaecher": [
            {
                "abschluss": "Master of Disaster",
                "fach": "Katastrophenmanagement",
                "fsem": 0
            }
        ],
        "vorname": "Florentius",
        "weiblich": false
    }
}
