{
    "ausfertigung": 1,
    "loecher": {
        "gremien": false,
        "sp": false
    },
    "nummer": 2160075,
    "semester": "Wintersemester 2017/2018",
    "stud": {
        "ausweistyp": "regulaer",
        "beurlaubt": false,
        "fakultaet": 7,
        "geburtsdatum": "15.12.1996",
        "matrikelnummer": 169004,
        "mehrfachausfertigung": 1,
        "mitglied_studierendenschaft": true,
        "nachname": "Reichart",
        "plzort": "53206 Bonn",
        "sternchen": 0,
        "strasse": "Reitschule 26",
        "studienfaecher": [
            {
                "abschluss": "Staatsex.",
                "fach": "Lebensmittelchemie",
                "fsem": 9
            }
        ],
        "vorname": "Conny",
        "weiblich": true
    }
}
