{
    "ausfertigung": 1,
    "loecher": {
        "gremien": false,
        "sp": false
    },
    "nummer": 2952497,
    "semester": "Wintersemester 2017/2018",
    "stud": {
        "ausweistyp": "regulaer",
        "beurlaubt": false,
        "fakultaet": 4,
        "geburtsdatum": "16.11.1987",
        "matrikelnummer": 2811810,
        "mehrfachausfertigung": 1,
        "mitglied_studierendenschaft": true,
        "nachname": "Artmann",
        "plzort": "53153 Bonn",
        "sternchen": 0,
        "strasse": "Breitscheidstra\u00dfe 5",
        "studienfaecher": [
            {
                "abschluss": "Staatsex.",
                "fach": "Medizin",
                "fsem": 12
            }
        ],
        "vorname": "Berna",
        "weiblich": true
    }
}
