{
    "ausfertigung": 1,
    "loecher": {
        "gremien": false,
        "sp": false
    },
    "nummer": "00000000",
    "semester": "Wintersemester 2016/2017",
    "stud": {
        "fakultaet": 6,
        "geburtsdatum": "14.01.1990",
        "matrikelnummer": 18140,
        "mehrfachausfertigung": 1,
        "nachname": "Herzog",
        "plzort": "53160 Bonn",
        "sternchen": 0,
        "strasse": "Bartsplatzl 6",
        "studienfaecher": [
            {
                "abschluss": "Master of Disaster",
                "fach": "Katastrophenmanagement",
                "fsem": 0
            }
        ],
        "vorname": "Reinhold",
        "weiblich": false
    }
}
