{
    "ausfertigung": 1,
    "loecher": {
        "gremien": false,
        "sp": false
    },
    "nummer": 2506053,
    "semester": "Wintersemester 2017/2018",
    "stud": {
        "ausweistyp": "regulaer",
        "beurlaubt": false,
        "fakultaet": 0,
        "geburtsdatum": "02.12.1993",
        "matrikelnummer": 2428674,
        "mehrfachausfertigung": 1,
        "mitglied_studierendenschaft": true,
        "nachname": "Henninger",
        "plzort": "57482 Wenden",
        "sternchen": 0,
        "strasse": "Am Bundleshof 3c",
        "studienfaecher": [
            {
                "abschluss": "Master of Arts",
                "fach": "Alt-Katholische und \u00d6kumenische Theologie",
                "fsem": 7
            },
            {
                "abschluss": "Master of Science",
                "fach": "Agricultural Science and Resource-Management in the Tropics and Subtropics",
                "fsem": 2
            }
        ],
        "vorname": "Christof",
        "weiblich": false
    }
}
