{
    "ausfertigung": 1,
    "loecher": {
        "gremien": false,
        "sp": false
    },
    "nummer": 2253261,
    "semester": "Wintersemester 2016/2017",
    "stud": {
        "beurlaubt": false,
        "fakultaet": 6,
        "geburtsdatum": "18.11.1993",
        "matrikelnummer": 12532,
        "mehrfachausfertigung": 1,
        "nachname": "Bruch",
        "plzort": "17375 Altwarp",
        "sternchen": 0,
        "strasse": "Th\u00e4terstra\u00dfe 8",
        "studienfaecher": [
            {
                "abschluss": "Master of Disaster",
                "fach": "Katastrophenmanagement",
                "fsem": 0
            }
        ],
        "vorname": "Karoline",
        "weiblich": true
    }
}
