{
    "ausfertigung": 1,
    "loecher": {
        "gremien": false,
        "sp": false
    },
    "nummer": 2604609,
    "semester": "Wintersemester 2016/2017",
    "stud": {
        "beurlaubt": false,
        "fakultaet": 5,
        "geburtsdatum": "19.05.1996",
        "matrikelnummer": 2198886,
        "mehrfachausfertigung": 1,
        "nachname": "Moosmann",
        "plzort": "01762 Hartmannsdorf-Reichenau",
        "sternchen": 0,
        "strasse": "Bodenstedtstra\u00dfe 12",
        "studienfaecher": [
            {
                "abschluss": "Master of Disaster",
                "fach": "Katastrophenmanagement",
                "fsem": 0
            }
        ],
        "vorname": "Adela",
        "weiblich": true
    }
}
