{
    "ausfertigung": 1,
    "loecher": {
        "gremien": false,
        "sp": false
    },
    "nummer": "00000000",
    "semester": "Sommersemester 2016",
    "stud": {
        "fakultaet": 3,
        "geburtsdatum": "09.01.1999",
        "matrikelnummer": 11526,
        "mehrfachausfertigung": 1,
        "nachname": "Haider",
        "plzort": "96193 Wachenroth",
        "sternchen": 0,
        "strasse": "Karl-Leicht-Str. 2",
        "studienfaecher": [
            {
                "abschluss": "Master of Disaster",
                "fach": "Katastrophenmanagement",
                "fsem": 0
            }
        ],
        "vorname": "Helmo",
        "weiblich": false
    }
}
