{
    "ausfertigung": 1,
    "loecher": {
        "gremien": false,
        "sp": false
    },
    "nummer": 2195973,
    "semester": "Wintersemester 2017/2018",
    "stud": {
        "ausweistyp": "regulaer",
        "beurlaubt": false,
        "fakultaet": 4,
        "geburtsdatum": "02.07.1995",
        "matrikelnummer": 3120413,
        "mehrfachausfertigung": 1,
        "mitglied_studierendenschaft": true,
        "nachname": "Weiler",
        "plzort": "53157 Bonn",
        "sternchen": 0,
        "strasse": "Lugaer Stra\u00dfe 28",
        "studienfaecher": [
            {
                "abschluss": "Staatsex.",
                "fach": "Zahnmedizin",
                "fsem": 1
            }
        ],
        "vorname": "Diethelm",
        "weiblich": false
    }
}
