{
    "ausfertigung": 1,
    "loecher": {
        "gremien": false,
        "sp": false
    },
    "nummer": 1667846,
    "semester": "Sommersemester 2017",
    "stud": {
        "ausweistyp": "regulaer",
        "beurlaubt": false,
        "fakultaet": 6,
        "geburtsdatum": "11.09.1993",
        "matrikelnummer": 1958342,
        "mehrfachausfertigung": 1,
        "mitglied_studierendenschaft": true,
        "nachname": "Heiser",
        "plzort": "83623 Dietramszell",
        "sternchen": 0,
        "strasse": "Kohlenstra\u00dfe 2",
        "studienfaecher": [
            {
                "abschluss": "Promotion",
                "fach": "Chemie",
                "fsem": 11
            }
        ],
        "vorname": "Radegundis",
        "weiblich": true
    }
}
