{
    "ausfertigung": 1,
    "loecher": {
        "gremien": false,
        "sp": false
    },
    "nummer": 1449043,
    "semester": "Wintersemester 2016/2017",
    "stud": {
        "beurlaubt": false,
        "fakultaet": 2,
        "geburtsdatum": "26.09.1999",
        "matrikelnummer": 2805554,
        "mehrfachausfertigung": 1,
        "nachname": "Zellner",
        "plzort": "53155 Bonn",
        "sternchen": 0,
        "strasse": "Erlichstr. 0",
        "studienfaecher": [
            {
                "abschluss": "Master of Disaster",
                "fach": "Katastrophenmanagement",
                "fsem": 0
            }
        ],
        "vorname": "Raimer",
        "weiblich": false
    }
}
