{
    "ausfertigung": 1,
    "loecher": {
        "gremien": true,
        "sp": false
    },
    "nummer": 2432784,
    "semester": "Wintersemester 2018/2019",
    "stud": {
        "ausweistyp": "regulaer",
        "beurlaubt": false,
        "fakultaet": 0,
        "geburtsdatum": "14.07.1993",
        "matrikelnummer": 12111,
        "mehrfachausfertigung": 1,
        "mitglied_studierendenschaft": true,
        "nachname": "Spangenberg",
        "plzort": "06268 Wei\u00dfenschirmbach",
        "sternchen": 0,
        "strasse": "Eigenheimweg 9",
        "studienfaecher": [
            {
                "abschluss": "Master of Science",
                "fach": "Life Science Informatics",
                "fsem": 9
            }
        ],
        "vorname": "Marielene",
        "weiblich": true
    }
}
