{
    "ausfertigung": 1,
    "loecher": {
        "gremien": true,
        "sp": true
    },
    "nummer": 2337010,
    "semester": "Wintersemester 2017/2018",
    "stud": {
        "ausweistyp": "weiterbildung",
        "beurlaubt": false,
        "fakultaet": 9,
        "geburtsdatum": "06.02.1995",
        "matrikelnummer": 2276778,
        "mehrfachausfertigung": 1,
        "mitglied_studierendenschaft": false,
        "nachname": "Schardt",
        "plzort": "88356 Ostrach",
        "sternchen": 0,
        "strasse": "Magdeburger Stra\u00dfe 3",
        "studienfaecher": [
            {
                "abschluss": "Master of Science",
                "fach": "Economics",
                "fsem": 10
            }
        ],
        "vorname": "Elgard",
        "weiblich": true
    }
}
