{
    "ausfertigung": 1,
    "loecher": {
        "gremien": false,
        "sp": false
    },
    "nummer": 2114008,
    "semester": "Wintersemester 2016/2017",
    "stud": {
        "ausweistyp": "regulaer",
        "beurlaubt": false,
        "fakultaet": 6,
        "geburtsdatum": "14.02.1994",
        "matrikelnummer": 2799490,
        "mehrfachausfertigung": 1,
        "mitglied_studierendenschaft": true,
        "nachname": "Rogge",
        "plzort": "53122 Bonn",
        "sternchen": 0,
        "strasse": "Ullersdorfer Stra\u00dfe 9",
        "studienfaecher": [
            {
                "abschluss": "Staatsex.",
                "fach": "Pharmazie",
                "fsem": 3
            }
        ],
        "vorname": "Burkhardt",
        "weiblich": false
    }
}
