{
    "ausfertigung": 1,
    "loecher": {
        "gremien": false,
        "sp": false
    },
    "nummer": 2295314,
    "semester": "Wintersemester 2018/2019",
    "stud": {
        "ausweistyp": "zweithoerer",
        "beurlaubt": false,
        "fakultaet": 2,
        "geburtsdatum": "28.10.1992",
        "matrikelnummer": 1920605,
        "mehrfachausfertigung": 1,
        "mitglied_studierendenschaft": true,
        "nachname": "Schilling",
        "plzort": "39291 Zeddenick",
        "sternchen": 0,
        "strasse": "Seitenstra\u00dfe 18",
        "studienfaecher": [
            {
                "abschluss": "Magister Theologiae (ev.)",
                "fach": "Evangelische Theologie",
                "fsem": 8
            }
        ],
        "vorname": "Emmeram",
        "weiblich": false
    }
}
